pdf_preview/__init__.py
pdf_preview/__main__.py
pdf_preview/logging.yaml
pdf_preview/main_window.py
pdf_preview/pdfjs-dist/build/pdf.js
pdf_preview/pdfjs-dist/build/pdf.js.map
pdf_preview/pdfjs-dist/build/pdf.worker.js
pdf_preview/pdfjs-dist/build/pdf.worker.js.map
pdf_preview/pdfjs-dist/LICENSE
pdf_preview/pdfjs-dist/web/cmaps/78-EUC-H.bcmap
pdf_preview/pdfjs-dist/web/cmaps/78-EUC-V.bcmap
pdf_preview/pdfjs-dist/web/cmaps/78-H.bcmap
pdf_preview/pdfjs-dist/web/cmaps/78-RKSJ-H.bcmap
pdf_preview/pdfjs-dist/web/cmaps/78-RKSJ-V.bcmap
pdf_preview/pdfjs-dist/web/cmaps/78-V.bcmap
pdf_preview/pdfjs-dist/web/cmaps/78ms-RKSJ-H.bcmap
pdf_preview/pdfjs-dist/web/cmaps/78ms-RKSJ-V.bcmap
pdf_preview/pdfjs-dist/web/cmaps/83pv-RKSJ-H.bcmap
pdf_preview/pdfjs-dist/web/cmaps/90ms-RKSJ-H.bcmap
pdf_preview/pdfjs-dist/web/cmaps/90ms-RKSJ-V.bcmap
pdf_preview/pdfjs-dist/web/cmaps/90msp-RKSJ-H.bcmap
pdf_preview/pdfjs-dist/web/cmaps/90msp-RKSJ-V.bcmap
pdf_preview/pdfjs-dist/web/cmaps/90pv-RKSJ-H.bcmap
pdf_preview/pdfjs-dist/web/cmaps/90pv-RKSJ-V.bcmap
pdf_preview/pdfjs-dist/web/cmaps/Add-H.bcmap
pdf_preview/pdfjs-dist/web/cmaps/Add-RKSJ-H.bcmap
pdf_preview/pdfjs-dist/web/cmaps/Add-RKSJ-V.bcmap
pdf_preview/pdfjs-dist/web/cmaps/Add-V.bcmap
pdf_preview/pdfjs-dist/web/cmaps/Adobe-CNS1-0.bcmap
pdf_preview/pdfjs-dist/web/cmaps/Adobe-CNS1-1.bcmap
pdf_preview/pdfjs-dist/web/cmaps/Adobe-CNS1-2.bcmap
pdf_preview/pdfjs-dist/web/cmaps/Adobe-CNS1-3.bcmap
pdf_preview/pdfjs-dist/web/cmaps/Adobe-CNS1-4.bcmap
pdf_preview/pdfjs-dist/web/cmaps/Adobe-CNS1-5.bcmap
pdf_preview/pdfjs-dist/web/cmaps/Adobe-CNS1-6.bcmap
pdf_preview/pdfjs-dist/web/cmaps/Adobe-CNS1-UCS2.bcmap
pdf_preview/pdfjs-dist/web/cmaps/Adobe-GB1-0.bcmap
pdf_preview/pdfjs-dist/web/cmaps/Adobe-GB1-1.bcmap
pdf_preview/pdfjs-dist/web/cmaps/Adobe-GB1-2.bcmap
pdf_preview/pdfjs-dist/web/cmaps/Adobe-GB1-3.bcmap
pdf_preview/pdfjs-dist/web/cmaps/Adobe-GB1-4.bcmap
pdf_preview/pdfjs-dist/web/cmaps/Adobe-GB1-5.bcmap
pdf_preview-0.3.5.dist-info/entry_points.txt
pdf_preview-0.3.5.dist-info/LICENSE
pdf_preview-0.3.5.dist-info/METADATA
pdf_preview-0.3.5.dist-info/WHEEL
pdf_preview-0.3.5.dist-info/RECORD
