Metadata-Version: 2.1
Name: pdf-preview
Version: 0.3.5
Summary: PDF Previewer for Excel / Word document.
Home-page: https://github.com/kkzk/pdf-preview
Author: kkzk
Author-email: shohachi.kakizaki@gmail.com
Requires-Python: >=3.12,<3.13
Classifier: Programming Language :: Python :: 3
Classifier: Programming Language :: Python :: 3.12
Requires-Dist: openpyxl (>=3.1.2,<4.0.0)
Requires-Dist: pypdf (>=4.0.2,<5.0.0)
Requires-Dist: pyside6 (>=6.6.2,<7.0.0)
Requires-Dist: pywin32 (>=306,<307)
Requires-Dist: pyyaml (>=6.0.2,<7.0.0)
